enveditor/__init__.py
enveditor/__sample.py
enveditor/__script_dialog.py
enveditor/__utils.py
enveditor/py.typed
arrangement/__init__.py
arrangement/__live.py
arrangement/__markers.py
arrangement/__selection.py
arrangement/__time.py
arrangement/py.typed
build_lib/midi_controller_scripting/callbacks/__init__.py
build_lib/midi_controller_scripting/callbacks/py.typed
channels/__init__.py
channels/__notes.py
channels/__properties.py
channels/__sequencer.py
channels/__ui.py
channels/py.typed
device/__device.py
device/__dispatch.py
device/__fl.py
device/__init__.py
device/__util.py
device/py.typed
fl_classes/__init__.py
fl_classes/py.typed
general/__fl_state.py
general/__init__.py
general/__undo.py
general/py.typed
launchMapPages/__init__.py
launchMapPages/py.typed
midi/__cc_flags.py
midi/__channel_types.py
midi/__event_editor_modes.py
midi/__ffnep_flags.py
midi/__get_color_flags.py
midi/__get_version_flags.py
midi/__gt_commands.py
midi/__gt_flags.py
midi/__init__.py
midi/__linked_event_flags.py
midi/__live_block_status.py
midi/__midi_codes.py
midi/__miscellaneous.py
midi/__mixer_link_channel_mode.py
midi/__mixer_peaks_mode.py
midi/__mixer_setTrackNumber_flags.py
midi/__mixer_solo_flags.py
midi/__on_dirty_channel_flags.py
midi/__on_refresh_flags.py
midi/__overlay_flags.py
midi/__pickup_modes.py
midi/__play_modes.py
midi/__plugin_get_name_flags.py
midi/__pme_flags.py
midi/__project_load_status.py
midi/__rec_events/__init__.py
midi/__rec_events/channel_properties.py
midi/__rec_events/global_properties.py
midi/__rec_events/mixer_properties.py
midi/__rec_events/playlist_properties.py
midi/__rec_events/process_flags.py
midi/__rec_events/ranges.py
midi/__rec_events/special.py
midi/__rec_events/ts404.py
midi/__scale_indexes.py
midi/__snap_modes.py
midi/__song_tick_modes.py
midi/__song_time.py
midi/__step_params.py
midi/__step_sequencer_loop.py
midi/__tlc_flags.py
midi/__track_info_flags.py
midi/__undo_flags.py
midi/__window_indexes.py
midi/py.typed
mixer/__eq.py
fl_studio_api_stubs-37.0.1.dist-info/LICENSE.md
fl_studio_api_stubs-37.0.1.dist-info/METADATA
fl_studio_api_stubs-37.0.1.dist-info/WHEEL
fl_studio_api_stubs-37.0.1.dist-info/RECORD
