Metadata-Version: 2.1
Name: fl-studio-api-stubs
Version: 37.0.1
Summary: Stub code, type definitions and documentation for the FL Studio Python API
Home-page: https://github.com/IL-Group/FL-Studio-Api-Stubs/issues
License: LGPL-3.0-only
Keywords: fl-studio,midi,api,documentation,stubs,fl,studio,daw,controller,image-line
Author: Maddy Guthridge
Author-email: hello@maddyguthridge.com
Requires-Python: >=3.10,<4.0
Classifier: Development Status :: 5 - Production/Stable
Classifier: Environment :: Other Environment
Classifier: Intended Audience :: Developers
Classifier: License :: OSI Approved :: GNU Lesser General Public License v3 (LGPLv3)
Classifier: License :: OSI Approved :: GNU Lesser General Public License v3 or later (LGPLv3+)
Classifier: Operating System :: OS Independent
Classifier: Programming Language :: Python :: 3
Classifier: Programming Language :: Python :: 3.10
Classifier: Programming Language :: Python :: 3.11
Classifier: Programming Language :: Python :: 3.12
Classifier: Topic :: Software Development :: Documentation
Classifier: Topic :: Software Development :: Libraries :: Application Frameworks
Classifier: Typing :: Stubs Only
Classifier: Typing :: Typed
Project-URL: Bug Tracker, https://github.com/IL-Group/FL-Studio-Api-Stubs/issues
Project-URL: Documentation, https://il-group.github.io/FL-Studio-API-Stubs/
Project-URL: Online Documentation, https://il-group.github.io/FL-Studio-API-Stubs/
Project-URL: Repository, https://github.com/IL-Group/FL-Studio-Api-Stubs/issues
